[
  {
    "country": "USSR",
    "units": [
      { "type": "attack", "image": "./img/unitsgame/b2.png" },
      { "type": "attack", "image": "./img/unitsgame/b2.png" },
      { "type": "attack", "image": "./img/unitsgame/b2.png" },
      { "type": "defense", "image": "./img/unitsgame/b2.png" },
      { "type": "defense", "image": "./img/unitsgame/b2.png" },
      { "type": "defense", "image": "./img/unitsgame/b2.png" }
    ]
  },
  {
    "country": "DEUTSCHLAND",
    "units": [
      { "type": "attack", "image": "./img/unitsgame/b2.png" },
      { "type": "attack", "image": "./img/unitsgame/b2.png" },
      { "type": "attack", "image": "./img/unitsgame/b2.png" },
      { "type": "defense", "image": "./img/unitsgame/b2.png" },
      { "type": "defense", "image": "./img/unitsgame/b2.png" },
      { "type": "defense", "image": "./img/unitsgame/b2.png" }
    ]
  },
  {
    "country": "USA",
    "units": [
      { "type": "attack", "image": "./img/unitsgame/b2.png" },
      { "type": "attack", "image": "./img/unitsgame/b2.png" },
      { "type": "attack", "image": "./img/unitsgame/b2.png" },
      { "type": "defense", "image": "./img/unitsgame/b2.png" },
      { "type": "defense", "image": "./img/unitsgame/b2.png" },
      { "type": "defense", "image": "./img/unitsgame/b2.png" }
    ]
  }
]